seperability/__init__.py
seperability/activations.py
seperability/data_classes.py
seperability/model.py
seperability/model_names.py
seperability/texts.py
seperability-0.1.3.dist-info/WHEEL
seperability-0.1.3.dist-info/METADATA
seperability-0.1.3.dist-info/RECORD
