Metadata-Version: 2.1
Name: seperability
Version: 0.1.3
Summary: Seperability of LLM Capabilities
Home-page: https://github.com/pesvut/seperability
Author: Nicky Pochinkov
Requires-Python: >=3.8,<4.0
Classifier: License :: OSI Approved :: MIT License
Classifier: Operating System :: OS Independent
Classifier: Programming Language :: Python :: 3
Classifier: Programming Language :: Python :: 3.8
Classifier: Programming Language :: Python :: 3.9
Classifier: Programming Language :: Python :: 3.10
Classifier: Programming Language :: Python :: 3.11
Classifier: Programming Language :: Python :: 3
Requires-Dist: accelerate (>=0.16.0,<0.17.0)
Requires-Dist: datasets (>=2.9.0,<3.0.0)
Requires-Dist: dict-deep (>=4.1.2,<5.0.0)
Requires-Dist: einops (>=0.6.0,<0.7.0)
Requires-Dist: evaluate (>=0.4.0,<0.5.0)
Requires-Dist: ipykernel (>=6.21.1,<7.0.0)
Requires-Dist: ipywidgets (>=8.0.4,<9.0.0)
Requires-Dist: matplotlib (>=3.6.3,<4.0.0)
Requires-Dist: numexpr (>=2.7.0,<3.0.0)
Requires-Dist: numpy (>=1.23,<2.0)
Requires-Dist: pandas (>=1.5.3,<2.0.0)
Requires-Dist: tensorboard (>=2.11.2,<3.0.0)
Requires-Dist: tensorboardx (>=2.5.1,<3.0.0)
Requires-Dist: torch (>=1.13.0,<2.0.0)
Requires-Dist: transformers (>=4.26.0,<5.0.0)
Requires-Dist: wandb (>=0.13.9,<0.14.0)
Requires-Dist: welford-torch (>=0.1.2,<0.2.0)
Requires-Dist: zstandard (>=0.19.0,<0.20.0)
Project-URL: Repository, https://github.com/pesvut/seperability
